{"data":{"site":{"siteMetadata":{"title":"Gritty Flyers Blog","author":"Brookes"}},"markdownRemark":{"id":"55f3f0f0-aeb5-5fc0-9ecc-ba01e878b0da","excerpt":"commands gatsby develop (local dev server with hmr) gatsby build gatsby server (normal server just to check) starters gatsby new uses gatsby…","html":"<h3>commands</h3>\n<ul>\n<li>gatsby develop (local dev server with hmr)</li>\n<li>gatsby build</li>\n<li>gatsby server (normal server just to check)</li>\n</ul>\n<h3>starters</h3>\n<ul>\n<li>gatsby new uses gatsby-starter-default</li>\n<li>gatsby new <dirname> &#x3C;repo_address></li>\n</ul>","frontmatter":{"title":"","date":null}}},"pageContext":{"slug":"/talk-notes/notes/","previous":{"fields":{"slug":"/mc-post/"},"frontmatter":{"title":"McPost"}},"next":null}}